{
  "width": 15,
  "height": 15,
  "grid": [
    [
      0,
      0,
      0,
      0,
      0,
      0,
      0,
      0,
      0,
      0,
      0,
      0,
      0,
      0,
      0
    ],
    [
      0,
      0,
      0,
      0,
      0,
      0,
      0,
      0,
      0,
      0,
      0,
      0,
      0,
      0,
      0
    ],
    [
      0,
      0,
      0,
      0,
      0,
      0,
      0,
      0,
      0,
      0,
      1,
      0,
      0,
      0,
      0
    ],
    [
      0,
      0,
      0,
      0,
      0,
      0,
      0,
      1,
      1,
      1,
      1,
      1,
      1,
      0,
      0
    ],
    [
      0,
      1,
      0,
      0,
      0,
      0,
      0,
      0,
      0,
      0,
      1,
      0,
      1,
      0,
      0
    ],
    [
      0,
      1,
      0,
      0,
      0,
      0,
      1,
      1,
      1,
      0,
      1,
      0,
      1,
      0,
      0
    ],
    [
      0,
      1,
      0,
      0,
      1,
      0,
      1,
      0,
      0,
      0,
      1,
      0,
      0,
      1,
      0
    ],
    [
      0,
      1,
      1,
      1,
      1,
      1,
      1,
      1,
      1,
      1,
      1,
      1,
      1,
      1,
      0
    ],
    [
      0,
      1,
      0,
      0,
      1,
      0,
      1,
      0,
      0,
      1,
      0,
      0,
      0,
      1,
      0
    ],
    [
      0,
      1,
      0,
      0,
      1,
      0,
      1,
      0,
      0,
      0,
      0,
      0,
      0,
      1,
      0
    ],
    [
      0,
      0,
      0,
      0,
      0,
      0,
      1,
      0,
      0,
      1,
      0,
      0,
      1,
      1,
      1
    ],
    [
      0,
      0,
      0,
      0,
      1,
      1,
      1,
      1,
      1,
      1,
      1,
      1,
      0,
      0,
      0
    ],
    [
      0,
      0,
      0,
      0,
      0,
      0,
      0,
      1,
      0,
      1,
      0,
      1,
      0,
      0,
      0
    ],
    [
      0,
      0,
      0,
      0,
      0,
      0,
      0,
      1,
      0,
      1,
      0,
      1,
      0,
      0,
      0
    ],
    [
      0,
      0,
      0,
      0,
      0,
      0,
      0,
      0,
      0,
      0,
      0,
      0,
      0,
      0,
      0
    ]
  ],
  "gridLetters": [
    [
      " ",
      " ",
      " ",
      " ",
      " ",
      " ",
      " ",
      " ",
      " ",
      " ",
      " ",
      " ",
      " ",
      " ",
      " "
    ],
    [
      " ",
      " ",
      " ",
      " ",
      " ",
      " ",
      " ",
      " ",
      " ",
      " ",
      " ",
      " ",
      " ",
      " ",
      " "
    ],
    [
      " ",
      " ",
      " ",
      " ",
      " ",
      " ",
      " ",
      " ",
      " ",
      " ",
      "W",
      " ",
      " ",
      " ",
      " "
    ],
    [
      " ",
      " ",
      " ",
      " ",
      " ",
      " ",
      " ",
      "I",
      "S",
      "L",
      "A",
      "N",
      "D",
      " ",
      " "
    ],
    [
      " ",
      "V",
      " ",
      " ",
      " ",
      " ",
      " ",
      " ",
      " ",
      " ",
      "L",
      " ",
      "U",
      " ",
      " "
    ],
    [
      " ",
      "B",
      " ",
      " ",
      " ",
      " ",
      "B",
      "A",
      "E",
      " ",
      "L",
      " ",
      "B",
      " ",
      " "
    ],
    [
      " ",
      "U",
      " ",
      " ",
      "E",
      " ",
      "E",
      " ",
      " ",
      " ",
      "E",
      " ",
      " ",
      "D",
      " "
    ],
    [
      " ",
      "C",
      "H",
      "O",
      "P",
      "P",
      "L",
      "E",
      "G",
      "A",
      "N",
      "G",
      "E",
      "R",
      " "
    ],
    [
      " ",
      "K",
      " ",
      " ",
      "I",
      " ",
      "I",
      " ",
      " ",
      "F",
      " ",
      " ",
      " ",
      "A",
      " "
    ],
    [
      " ",
      "S",
      " ",
      " ",
      "C",
      " ",
      "N",
      " ",
      " ",
      " ",
      " ",
      " ",
      " ",
      "M",
      " "
    ],
    [
      " ",
      " ",
      " ",
      " ",
      " ",
      " ",
      "D",
      " ",
      " ",
      "W",
      " ",
      " ",
      "Y",
      "A",
      "M"
    ],
    [
      " ",
      " ",
      " ",
      " ",
      "T",
      "H",
      "A",
      "I",
      "L",
      "A",
      "N",
      "D",
      " ",
      " ",
      " "
    ],
    [
      " ",
      " ",
      " ",
      " ",
      " ",
      " ",
      " ",
      "S",
      " ",
      "L",
      " ",
      "A",
      " ",
      " ",
      " "
    ],
    [
      " ",
      " ",
      " ",
      " ",
      " ",
      " ",
      " ",
      "S",
      " ",
      "Z",
      " ",
      "P",
      " ",
      " ",
      " "
    ],
    [
      " ",
      " ",
      " ",
      " ",
      " ",
      " ",
      " ",
      " ",
      " ",
      " ",
      " ",
      " ",
      " ",
      " ",
      " "
    ]
  ],
  "numbers": {
    "2,10": 1,
    "3,7": 2,
    "3,12": 3,
    "4,1": 4,
    "5,6": 5,
    "6,4": 6,
    "6,13": 7,
    "7,1": 8,
    "7,9": 9,
    "10,9": 10,
    "10,12": 11,
    "11,4": 12,
    "11,7": 13,
    "11,11": 14
  },
  "words": {
    "across": {
      "8": {
        "clue": "TikTok term for an 'ugly' lookalike",
        "answer": "CHOPPLEGANGER",
        "row": 7,
        "col": 1
      },
      "2": {
        "clue": "Fortnite Creative location",
        "answer": "ISLAND",
        "row": 3,
        "col": 7
      },
      "12": {
        "clue": "Setting for 'White Lotus' Season 3",
        "answer": "THAILAND",
        "row": 11,
        "col": 4
      },
      "5": {
        "clue": "Significant other",
        "answer": "BAE",
        "row": 5,
        "col": 6
      },
      "11": {
        "clue": "'Survivor' winner ___ Yam Arocho",
        "answer": "YAM",
        "row": 10,
        "col": 12
      }
    },
    "down": {
      "9": {
        "clue": "Emphatic slang acronym",
        "answer": "AF",
        "row": 7,
        "col": 9
      },
      "4": {
        "clue": "Fortnite currency",
        "answer": "VBUCKS",
        "row": 4,
        "col": 1
      },
      "5": {
        "clue": "Spa manager in 'White Lotus' S3",
        "answer": "BELINDA",
        "row": 5,
        "col": 6
      },
      "1": {
        "clue": "Country star Morgan",
        "answer": "WALLEN",
        "row": 2,
        "col": 10
      },
      "6": {
        "clue": "Fortnite developer",
        "answer": "EPIC",
        "row": 6,
        "col": 4
      },
      "3": {
        "clue": "A win, short for 'W'",
        "answer": "DUB",
        "row": 3,
        "col": 12
      },
      "7": {
        "clue": "Genre of 'The White Lotus'",
        "answer": "DRAMA",
        "row": 6,
        "col": 13
      },
      "10": {
        "clue": "Minnesota Governor Tim",
        "answer": "WALZ",
        "row": 10,
        "col": 9
      },
      "13": {
        "clue": "Crew-11 left this station early",
        "answer": "ISS",
        "row": 11,
        "col": 7
      },
      "14": {
        "clue": "Handshake gesture (slang)",
        "answer": "DAP",
        "row": 11,
        "col": 11
      }
    }
  }
}